text_saver_utilss_sss/__init__.py
text_saver_utilss_sss/main.py
text_saver_utilsss_sss-1.0.0.dist-info/LICENSE
text_saver_utilsss_sss-1.0.0.dist-info/METADATA
text_saver_utilsss_sss-1.0.0.dist-info/WHEEL
text_saver_utilsss_sss-1.0.0.dist-info/top_level.txt
text_saver_utilsss_sss-1.0.0.dist-info/RECORD
